{"config": {"view": {"continuousWidth": 300, "continuousHeight": 300}}, "data": {"name": "data-632457f703554976ea7341dc28be3127"}, "mark": {"type": "bar"}, "encoding": {"tooltip": [{"field": "Action", "type": "nominal"}, {"field": "Count", "type": "quantitative"}], "x": {"field": "Action", "title": "Type of Action", "type": "nominal"}, "y": {"field": "Count", "title": "Number of Occurrences", "type": "quantitative"}}, "height": 400, "title": "Distribution of Types of Actions", "width": 800, "$schema": "https://vega.github.io/schema/vega-lite/v5.17.0.json", "datasets": {"data-632457f703554976ea7341dc28be3127": [{"Action": "Suspension", "Count": 80}, {"Action": "Refuse To Renew", "Count": 79}, {"Action": "Probation", "Count": 74}, {"Action": "Reprimand", "Count": 38}, {"Action": "Fine", "Count": 37}, {"Action": "Revocation", "Count": 11}, {"Action": "Probation w/o Monitoring", "Count": 11}, {"Action": "due to criminal history & failure to disclose", "Count": 4}, {"Action": "due to criminal history and failure to disclose", "Count": 3}, {"Action": "due to criminal conviction history and failure to disclose.", "Count": 2}, {"Action": "Termination", "Count": 1}, {"Action": "Summary Suspension", "Count": 1}, {"Action": "due to criminal history and failure to disclose.", "Count": 1}]}}